explorerscript_parser.cp313-win_amd64.pyd
explorerscript/__init__.py
explorerscript/common_syntax.py
explorerscript/error.py
explorerscript/explorerscript_reader.py
explorerscript/included_usage_map.py
explorerscript/macro.py
explorerscript/py.typed
explorerscript/source_map.py
explorerscript/source_map_visualizer.py
explorerscript/syntax_error_listener.py
explorerscript/util.py
explorerscript/cli/__init__.py
explorerscript/cli/compile.py
explorerscript/cli/decompile.py
explorerscript/pygments/__init__.py
explorerscript/pygments/expslexer.py
explorerscript/ssb_converting/__init__.py
explorerscript/ssb_converting/ssb_compiler.py
explorerscript/ssb_converting/ssb_data_types.py
explorerscript/ssb_converting/ssb_decompiler.py
explorerscript/ssb_converting/ssb_special_ops.py
explorerscript/ssb_converting/util.py
explorerscript/ssb_converting/compiler/__init__.py
explorerscript/ssb_converting/compiler/label_finalizer.py
explorerscript/ssb_converting/compiler/label_jump_to_remover.py
explorerscript/ssb_converting/compiler/meta_attributes.py
explorerscript/ssb_converting/compiler/utils.py
explorerscript/ssb_converting/compiler/compile_handlers/__init__.py
explorerscript/ssb_converting/compiler/compile_handlers/abstract.py
explorerscript/ssb_converting/compiler/compile_handlers/null.py
explorerscript/ssb_converting/compiler/compile_handlers/assignments/__init__.py
explorerscript/ssb_converting/compiler/compile_handlers/assignments/assignment_adventure_log.py
explorerscript/ssb_converting/compiler/compile_handlers/assignments/assignment_clear.py
explorerscript/ssb_converting/compiler/compile_handlers/assignments/assignment_dungeon_mode.py
explorerscript/ssb_converting/compiler/compile_handlers/assignments/assignment_initial.py
explorerscript/ssb_converting/compiler/compile_handlers/assignments/assignment_regular.py
explorerscript/ssb_converting/compiler/compile_handlers/assignments/assignment_reset.py
explorerscript-0.2.4.dist-info/licenses/LICENSE
explorerscript-0.2.4.dist-info/METADATA
explorerscript-0.2.4.dist-info/WHEEL
explorerscript-0.2.4.dist-info/entry_points.txt
explorerscript-0.2.4.dist-info/top_level.txt
explorerscript-0.2.4.dist-info/RECORD
