Metadata-Version: 2.4
Name: explorerscript
Version: 0.2.4
Summary: ExplorerScript and SSBScript: Script languages for decompiled SSB (Pokémon Mystery Dungeon Explorers of Sky)
Author-email: "Marco \"Capypara\" Köpcke" <hello@capypara.de>
License: MIT
Project-URL: Homepage, https://skytemple.org
Project-URL: Announcements, https://blog.skytemple.org
Project-URL: Documentation, https://wiki.skytemple.org
Project-URL: Repository, https://github.com/SkyTemple/ExplorerScript.git
Project-URL: Issues, https://github.com/SkyTemple/ExplorerScript/issues
Project-URL: Discord, https://discord.gg/skytemple
Keywords: rom-hacking,game-modding,skytemple
Classifier: Development Status :: 4 - Beta
Classifier: Programming Language :: Python
Classifier: License :: OSI Approved :: MIT License
Classifier: Programming Language :: Python :: 3.10
Classifier: Programming Language :: Python :: 3.11
Classifier: Programming Language :: Python :: 3.12
Classifier: Programming Language :: Python :: 3.13
Requires-Python: >=3.10
License-File: LICENSE
Requires-Dist: igraph==0.11.8
Requires-Dist: typing_extensions>=4.0; python_version < "3.10"
Provides-Extra: pygments
Requires-Dist: pygments>=2.6.1; extra == "pygments"
Dynamic: license-file
